gpt_neox_package/__init__.py
gpt_neox_package/configuration_gpt_neox.py
gpt_neox_package/modelling_gpt_neox_pairwise.py
gpt_pairwise/__init__.py
gpt_pairwise/configuration_gpt_neox.py
gpt_pairwise/modelling_gpt_neox_pairwise.py
gpt_neox_package-0.1.1.dist-info/LICENSE
gpt_neox_package-0.1.1.dist-info/METADATA
gpt_neox_package-0.1.1.dist-info/WHEEL
gpt_neox_package-0.1.1.dist-info/top_level.txt
gpt_neox_package-0.1.1.dist-info/RECORD
