Metadata-Version: 2.1
Name: gpt_neox_package
Version: 0.1.1
Summary: Custom extension for the transformers library including GPTNeoX models
Author: Ivan
Author-email: ivan.okunevich@gmail.com
Requires-Python: >=3.6
License-File: LICENSE
